odoo/addons/l10n_ro_account_bank_statement_import_mt940_bcr/README.rst
odoo/addons/l10n_ro_account_bank_statement_import_mt940_bcr/__init__.py
odoo/addons/l10n_ro_account_bank_statement_import_mt940_bcr/__manifest__.py
odoo/addons/l10n_ro_account_bank_statement_import_mt940_bcr/i18n/l10n_ro_account_bank_statement_import_mt940_bcr.pot
odoo/addons/l10n_ro_account_bank_statement_import_mt940_bcr/models/__init__.py
odoo/addons/l10n_ro_account_bank_statement_import_mt940_bcr/models/account_bank_statement_import.py
odoo/addons/l10n_ro_account_bank_statement_import_mt940_bcr/models/account_journal.py
odoo/addons/l10n_ro_account_bank_statement_import_mt940_bcr/models/mt940.py
odoo/addons/l10n_ro_account_bank_statement_import_mt940_bcr/readme/CONTRIBUTORS.rst
odoo/addons/l10n_ro_account_bank_statement_import_mt940_bcr/readme/DESCRIPTION.rst
odoo/addons/l10n_ro_account_bank_statement_import_mt940_bcr/static/description/icon.png
odoo/addons/l10n_ro_account_bank_statement_import_mt940_bcr/static/description/icon.svg
odoo/addons/l10n_ro_account_bank_statement_import_mt940_bcr/static/description/index.html
odoo/addons/l10n_ro_account_bank_statement_import_mt940_bcr/test_files/test_file_bcr.STA
odoo/addons/l10n_ro_account_bank_statement_import_mt940_bcr/tests/__init__.py
odoo/addons/l10n_ro_account_bank_statement_import_mt940_bcr/tests/test_import_bank_statement.py
odoo14_addon_l10n_ro_account_bank_statement_import_mt940_bcr-14.0.1.2.0.dist-info/METADATA
odoo14_addon_l10n_ro_account_bank_statement_import_mt940_bcr-14.0.1.2.0.dist-info/WHEEL
odoo14_addon_l10n_ro_account_bank_statement_import_mt940_bcr-14.0.1.2.0.dist-info/top_level.txt
odoo14_addon_l10n_ro_account_bank_statement_import_mt940_bcr-14.0.1.2.0.dist-info/RECORD
